serpente.py
python_serpente-2.0.dist-info/LICENSE
python_serpente-2.0.dist-info/METADATA
python_serpente-2.0.dist-info/WHEEL
python_serpente-2.0.dist-info/RECORD
